<PAMDataset>
  <Metadata>
    <MDI key="DataType">Generic</MDI>
  </Metadata>
  <PAMRasterBand band="1">
    <Description>nd</Description>
    <Histograms>
      <HistItem>
        <HistMin>0.1418364644050598</HistMin>
        <HistMax>0.8098812699317932</HistMax>
        <BucketCount>256</BucketCount>
        <IncludeOutOfRange>1</IncludeOutOfRange>
        <Approximate>0</Approximate>
        <HistCounts>2|0|0|0|0|0|0|0|0|0|0|0|0|0|0|0|0|0|0|0|0|2|0|4|0|0|0|0|0|1|0|4|0|0|0|0|0|4|5|0|1|0|0|2|4|8|1|18|5|1|3|9|13|1|17|9|8|5|8|12|17|15|1|16|12|21|27|20|15|18|36|18|36|27|13|34|36|34|27|34|28|32|43|31|60|44|43|47|57|62|79|60|70|69|81|90|71|101|59|96|69|67|82|73|84|78|64|82|97|99|79|106|100|90|83|129|106|91|77|130|131|142|89|80|122|106|81|107|154|95|115|122|130|134|152|104|112|128|116|117|90|85|138|131|146|88|85|86|85|135|82|103|91|70|126|77|106|88|71|135|95|128|111|84|94|105|93|58|95|98|81|91|95|68|68|85|58|86|57|75|53|61|57|67|67|52|46|78|75|43|57|29|58|58|55|33|27|53|35|63|11|40|24|13|32|35|15|14|26|28|20|21|34|21|18|27|20|15|16|20|11|13|19|21|15|4|4|5|7|4|12|16|6|2|0|8|3|0|4|4|4|0|4|0|4|4|4|4|0|0|0|0|0|0|0|4</HistCounts>
      </HistItem>
    </Histograms>
    <Metadata>
      <MDI key="BandName">nd</MDI>
      <MDI key="RepresentationType">ATHEMATIC</MDI>
      <MDI key="STATISTICS_COVARIANCES">0.009813875222409426</MDI>
      <MDI key="STATISTICS_EXCLUDEDVALUES"></MDI>
      <MDI key="STATISTICS_MAXIMUM">0.80988126993179</MDI>
      <MDI key="STATISTICS_MEAN">0.50677868764927</MDI>
      <MDI key="STATISTICS_MINIMUM">0.14183646440506</MDI>
      <MDI key="STATISTICS_SKIPFACTORX">1</MDI>
      <MDI key="STATISTICS_SKIPFACTORY">1</MDI>
      <MDI key="STATISTICS_STDDEV">0.099065005034116</MDI>
    </Metadata>
  </PAMRasterBand>
</PAMDataset>
