<PAMDataset>
  <Metadata>
    <MDI key="DataType">Generic</MDI>
  </Metadata>
  <PAMRasterBand band="1">
    <Description>nd</Description>
    <Histograms>
      <HistItem>
        <HistMin>0.06150896474719048</HistMin>
        <HistMax>0.3834087550640106</HistMax>
        <BucketCount>256</BucketCount>
        <IncludeOutOfRange>1</IncludeOutOfRange>
        <Approximate>0</Approximate>
        <HistCounts>7|3|4|0|2|0|4|8|2|9|25|15|14|6|28|11|13|23|20|11|10|23|14|21|34|18|13|12|35|14|23|22|24|21|17|18|35|19|32|35|20|31|56|37|36|59|22|42|27|67|55|51|62|55|59|52|62|67|34|74|65|59|90|66|54|82|99|102|79|82|85|87|86|85|133|107|136|112|106|151|165|115|131|108|134|116|139|121|112|167|148|133|121|117|128|117|85|99|135|154|149|147|122|142|130|151|93|74|103|77|65|103|81|90|64|83|78|79|75|96|88|74|78|104|99|56|76|72|61|74|72|78|64|44|31|45|77|62|64|51|40|44|55|43|24|46|23|23|16|34|19|35|54|29|21|13|36|33|27|29|14|11|20|20|12|20|12|9|23|21|7|10|10|16|13|2|12|15|3|4|3|2|0|4|0|7|4|7|10|2|12|7|0|8|0|0|0|0|4|8|7|13|6|22|4|12|4|0|4|0|5|12|8|1|12|6|0|0|4|0|4|4|0|0|4|8|0|4|3|4|0|3|4|0|0|4|0|0|0|0|4|0|0|0|0|0|0|0|0|0|0|0|0|0|2|3</HistCounts>
      </HistItem>
    </Histograms>
    <Metadata>
      <MDI key="BandName">nd</MDI>
      <MDI key="RepresentationType">ATHEMATIC</MDI>
      <MDI key="STATISTICS_COVARIANCES">0.002256162923242415</MDI>
      <MDI key="STATISTICS_EXCLUDEDVALUES"></MDI>
      <MDI key="STATISTICS_MAXIMUM">0.38340875506401</MDI>
      <MDI key="STATISTICS_MEAN">0.18271297377858</MDI>
      <MDI key="STATISTICS_MINIMUM">0.06150896474719</MDI>
      <MDI key="STATISTICS_SKIPFACTORX">1</MDI>
      <MDI key="STATISTICS_SKIPFACTORY">1</MDI>
      <MDI key="STATISTICS_STDDEV">0.047499083393708</MDI>
    </Metadata>
  </PAMRasterBand>
</PAMDataset>
