<PAMDataset>
  <Metadata>
    <MDI key="DataType">Generic</MDI>
  </Metadata>
  <PAMRasterBand band="1">
    <Description>nd</Description>
    <Histograms>
      <HistItem>
        <HistMin>-0.1407357752323151</HistMin>
        <HistMax>0.6814357042312622</HistMax>
        <BucketCount>256</BucketCount>
        <IncludeOutOfRange>1</IncludeOutOfRange>
        <Approximate>0</Approximate>
        <HistCounts>1|0|0|0|0|0|0|0|0|0|0|0|0|0|0|2|0|1|0|0|0|0|0|0|2|0|0|0|0|0|1|0|0|0|1|0|2|1|1|0|1|0|0|1|0|0|0|0|1|1|0|0|5|0|0|0|1|2|0|1|1|1|0|0|1|8|5|2|2|0|0|4|2|1|2|0|3|0|2|5|2|5|1|5|2|16|10|6|1|3|4|3|6|10|3|3|3|3|10|9|7|2|8|11|15|9|12|23|28|7|9|17|12|15|18|14|24|10|44|24|51|31|57|49|57|57|49|73|68|81|88|73|91|124|112|125|156|121|169|186|163|213|176|223|251|252|217|244|242|286|329|318|271|308|339|278|355|334|372|292|265|351|376|362|394|376|387|396|379|347|339|341|397|340|345|341|301|290|294|336|310|318|244|280|193|222|234|204|247|208|205|152|192|101|115|132|76|97|90|93|64|37|37|41|40|29|32|19|41|32|26|25|36|19|17|21|9|11|12|1|8|4|4|14|3|0|2|4|3|0|2|5|0|0|0|3|0|4|4|0|3|0|8|0|0|0|0|1|0|0|0|0|0|0|0|3</HistCounts>
      </HistItem>
    </Histograms>
    <Metadata>
      <MDI key="BandName">nd</MDI>
      <MDI key="RepresentationType">ATHEMATIC</MDI>
      <MDI key="STATISTICS_COVARIANCES">0.004997628868358417</MDI>
      <MDI key="STATISTICS_EXCLUDEDVALUES"></MDI>
      <MDI key="STATISTICS_MAXIMUM">0.68143570423126</MDI>
      <MDI key="STATISTICS_MEAN">0.38789730515102</MDI>
      <MDI key="STATISTICS_MINIMUM">-0.14073577523232</MDI>
      <MDI key="STATISTICS_SKIPFACTORX">1</MDI>
      <MDI key="STATISTICS_SKIPFACTORY">1</MDI>
      <MDI key="STATISTICS_STDDEV">0.070693909697784</MDI>
    </Metadata>
  </PAMRasterBand>
</PAMDataset>
