<PAMDataset>
  <Metadata>
    <MDI key="DataType">Generic</MDI>
  </Metadata>
  <PAMRasterBand band="1">
    <Description>nd</Description>
    <Histograms>
      <HistItem>
        <HistMin>0.05355208739638329</HistMin>
        <HistMax>0.821878969669342</HistMax>
        <BucketCount>256</BucketCount>
        <IncludeOutOfRange>1</IncludeOutOfRange>
        <Approximate>0</Approximate>
        <HistCounts>2|0|0|0|0|0|0|0|0|0|0|0|0|0|0|0|3|0|0|0|0|0|0|0|0|0|0|0|0|3|1|0|0|0|1|0|0|3|0|5|0|5|3|2|5|1|5|2|1|0|1|0|2|4|0|0|5|3|2|1|7|6|2|1|8|4|1|4|8|6|1|2|6|5|5|7|4|8|11|7|10|5|8|6|15|12|12|9|13|2|11|17|15|11|11|1|10|10|14|11|9|14|31|25|11|15|26|39|22|19|18|10|17|27|30|24|24|31|21|36|34|50|41|31|26|55|29|31|41|39|73|45|71|76|80|69|71|76|64|82|67|98|95|71|82|91|119|88|124|94|112|122|107|158|119|111|120|137|145|141|115|169|197|136|148|129|141|209|208|184|217|197|201|148|208|216|180|231|207|185|220|223|210|203|256|226|225|230|269|215|264|228|241|231|236|293|272|223|229|244|280|233|226|240|231|210|171|164|231|153|209|144|175|197|178|149|163|112|133|116|154|128|126|128|118|124|144|101|156|119|116|99|81|79|108|65|83|47|47|74|42|36|33|67|20|54|29|18|16|14|10|8|8|14|0|4</HistCounts>
      </HistItem>
    </Histograms>
    <Metadata>
      <MDI key="BandName">nd</MDI>
      <MDI key="RepresentationType">ATHEMATIC</MDI>
      <MDI key="STATISTICS_COVARIANCES">0.01038475364614467</MDI>
      <MDI key="STATISTICS_EXCLUDEDVALUES"></MDI>
      <MDI key="STATISTICS_MAXIMUM">0.82187896966934</MDI>
      <MDI key="STATISTICS_MEAN">0.60603545862306</MDI>
      <MDI key="STATISTICS_MINIMUM">0.053552087396383</MDI>
      <MDI key="STATISTICS_SKIPFACTORX">1</MDI>
      <MDI key="STATISTICS_SKIPFACTORY">1</MDI>
      <MDI key="STATISTICS_STDDEV">0.10190561145562</MDI>
    </Metadata>
  </PAMRasterBand>
</PAMDataset>
