<PAMDataset>
  <Metadata>
    <MDI key="DataType">Generic</MDI>
  </Metadata>
  <PAMRasterBand band="1">
    <Description>nd</Description>
    <Histograms>
      <HistItem>
        <HistMin>-0.2200272083282471</HistMin>
        <HistMax>0.3837516903877258</HistMax>
        <BucketCount>256</BucketCount>
        <IncludeOutOfRange>1</IncludeOutOfRange>
        <Approximate>0</Approximate>
        <HistCounts>1|0|0|0|0|0|0|0|0|0|0|0|0|0|0|0|0|0|0|1|0|0|0|0|0|0|0|0|0|0|1|1|0|0|0|0|0|0|0|1|0|0|0|0|0|0|2|0|2|1|0|0|0|2|0|0|0|0|0|0|0|1|0|0|0|1|2|0|1|5|7|0|2|4|5|2|6|9|10|0|4|1|4|8|7|7|4|10|10|10|3|13|4|11|20|5|10|17|23|7|16|22|28|14|12|19|20|24|43|41|35|45|59|38|49|70|48|59|55|68|48|63|86|90|86|84|91|111|121|114|172|193|154|203|131|152|179|231|260|270|219|296|250|232|347|233|310|254|307|322|298|328|359|312|270|307|251|303|341|263|293|228|271|192|253|238|246|190|167|141|143|131|123|103|142|97|94|104|70|75|32|38|47|27|30|24|30|31|23|25|20|23|18|22|20|9|15|5|3|7|6|0|9|0|12|3|1|5|2|1|2|0|0|0|0|0|0|1|0|0|0|0|0|0|0|1|0|0|0|0|0|0|0|0|0|0|0|0|0|0|0|0|0|0|0|1|0|0|0|1|0|0|0|0|0|1</HistCounts>
      </HistItem>
    </Histograms>
    <Metadata>
      <MDI key="BandName">nd</MDI>
      <MDI key="RepresentationType">ATHEMATIC</MDI>
      <MDI key="STATISTICS_COVARIANCES">0.002192455524155451</MDI>
      <MDI key="STATISTICS_EXCLUDEDVALUES"></MDI>
      <MDI key="STATISTICS_MAXIMUM">0.38375169038773</MDI>
      <MDI key="STATISTICS_MEAN">0.13250546098135</MDI>
      <MDI key="STATISTICS_MINIMUM">-0.22002720832825</MDI>
      <MDI key="STATISTICS_SKIPFACTORX">1</MDI>
      <MDI key="STATISTICS_SKIPFACTORY">1</MDI>
      <MDI key="STATISTICS_STDDEV">0.046823664147047</MDI>
    </Metadata>
  </PAMRasterBand>
</PAMDataset>
