<PAMDataset>
  <Metadata>
    <MDI key="DataType">Generic</MDI>
  </Metadata>
  <PAMRasterBand band="1">
    <Description>nd</Description>
    <Histograms>
      <HistItem>
        <HistMin>-0.1908467710018158</HistMin>
        <HistMax>0.8055947422981262</HistMax>
        <BucketCount>256</BucketCount>
        <IncludeOutOfRange>1</IncludeOutOfRange>
        <Approximate>0</Approximate>
        <HistCounts>2|2|0|0|2|0|0|0|0|0|0|0|0|0|0|2|7|0|4|4|4|0|0|0|0|0|0|0|0|0|7|0|12|6|0|8|4|4|4|4|9|0|8|0|11|15|8|0|8|4|4|0|8|8|10|8|20|8|4|2|0|10|6|6|16|7|4|2|8|8|32|22|9|10|11|24|0|12|19|23|13|14|11|13|19|12|17|30|15|48|33|30|25|51|35|22|27|40|46|56|25|70|20|59|55|46|48|69|56|78|101|101|84|134|124|105|122|148|144|177|204|207|190|204|234|215|236|263|311|269|247|263|252|256|278|278|264|255|239|299|212|261|177|259|260|224|191|125|148|116|111|191|91|105|78|97|69|97|98|74|93|86|57|100|47|39|45|68|46|46|50|39|52|62|47|50|29|39|34|32|33|35|23|24|19|36|18|35|25|28|14|19|8|4|21|45|7|14|25|20|32|23|25|17|28|12|16|24|31|19|20|13|10|14|22|12|11|9|12|12|8|13|7|5|9|15|7|5|4|2|7|3|1|3|6|2|7|7|1|3|2|0|1|1|2|5|1|0|1|1|2|0|0|0|0|1</HistCounts>
      </HistItem>
    </Histograms>
    <Metadata>
      <MDI key="BandName">nd</MDI>
      <MDI key="RepresentationType">ATHEMATIC</MDI>
      <MDI key="STATISTICS_COVARIANCES">0.01357652911899596</MDI>
      <MDI key="STATISTICS_EXCLUDEDVALUES"></MDI>
      <MDI key="STATISTICS_MAXIMUM">0.80559474229813</MDI>
      <MDI key="STATISTICS_MEAN">0.34214234180963</MDI>
      <MDI key="STATISTICS_MINIMUM">-0.19084677100182</MDI>
      <MDI key="STATISTICS_SKIPFACTORX">1</MDI>
      <MDI key="STATISTICS_SKIPFACTORY">1</MDI>
      <MDI key="STATISTICS_STDDEV">0.11651836387023</MDI>
    </Metadata>
  </PAMRasterBand>
</PAMDataset>
