<PAMDataset>
  <Metadata>
    <MDI key="DataType">Generic</MDI>
  </Metadata>
  <PAMRasterBand band="1">
    <Description>nd</Description>
    <Histograms>
      <HistItem>
        <HistMin>0.05512965843081474</HistMin>
        <HistMax>0.8258901238441467</HistMax>
        <BucketCount>256</BucketCount>
        <IncludeOutOfRange>1</IncludeOutOfRange>
        <Approximate>0</Approximate>
        <HistCounts>2|0|0|0|0|0|0|1|0|1|0|2|1|0|3|1|2|2|0|1|2|0|3|1|2|0|4|0|1|0|1|2|3|6|2|3|3|0|8|6|9|7|7|3|7|1|3|8|3|1|5|9|12|14|3|4|5|8|13|15|16|14|2|18|17|16|20|16|23|21|23|17|21|36|29|33|33|38|41|46|55|44|48|66|68|64|73|73|56|49|75|70|65|76|98|72|91|79|116|101|119|109|106|128|130|191|143|177|160|146|190|188|198|228|213|274|250|219|262|209|265|238|284|272|278|241|253|235|288|266|241|336|327|323|282|219|329|301|232|292|362|355|327|259|249|283|285|357|359|324|321|330|361|316|352|387|392|344|259|297|358|347|295|325|375|350|342|392|298|326|291|336|455|376|305|365|288|314|344|311|334|303|299|334|270|337|332|301|274|259|278|262|280|270|247|258|305|176|284|279|239|201|255|279|271|230|220|200|186|217|175|173|190|165|123|162|167|131|150|126|159|116|101|111|117|76|91|56|65|55|57|62|48|51|59|39|40|14|40|14|11|24|13|6|9|21|4|8|12|4|2|0|0|0|0|2</HistCounts>
      </HistItem>
    </Histograms>
    <Metadata>
      <MDI key="BandName">nd</MDI>
      <MDI key="RepresentationType">ATHEMATIC</MDI>
      <MDI key="STATISTICS_COVARIANCES">0.01291273062359907</MDI>
      <MDI key="STATISTICS_EXCLUDEDVALUES"></MDI>
      <MDI key="STATISTICS_MAXIMUM">0.82589012384415</MDI>
      <MDI key="STATISTICS_MEAN">0.53500072726348</MDI>
      <MDI key="STATISTICS_MINIMUM">0.055129658430815</MDI>
      <MDI key="STATISTICS_SKIPFACTORX">1</MDI>
      <MDI key="STATISTICS_SKIPFACTORY">1</MDI>
      <MDI key="STATISTICS_STDDEV">0.11363419654135</MDI>
    </Metadata>
  </PAMRasterBand>
</PAMDataset>
