<PAMDataset>
  <Metadata>
    <MDI key="DataType">Generic</MDI>
  </Metadata>
  <PAMRasterBand band="1">
    <Description>nd</Description>
    <Histograms>
      <HistItem>
        <HistMin>-0.1025332063436508</HistMin>
        <HistMax>0.5407800078392029</HistMax>
        <BucketCount>256</BucketCount>
        <IncludeOutOfRange>1</IncludeOutOfRange>
        <Approximate>0</Approximate>
        <HistCounts>2|2|0|0|0|0|0|0|0|0|0|2|0|0|3|0|0|0|0|0|4|0|4|0|0|0|4|0|2|2|4|0|8|13|0|6|9|16|8|11|7|8|20|20|13|21|24|38|31|52|20|44|83|42|41|98|66|52|65|92|78|75|129|77|95|116|147|98|123|121|144|163|183|197|207|151|240|223|202|258|323|257|304|285|301|317|288|398|293|438|356|365|400|304|282|359|411|360|374|382|369|318|292|303|303|363|288|340|281|271|253|293|267|229|252|187|248|210|168|171|113|136|154|119|126|118|114|108|110|103|95|104|85|73|40|50|68|65|47|55|35|41|66|38|37|18|19|44|28|15|25|26|20|6|15|12|23|14|22|10|7|9|15|11|17|2|7|10|12|1|4|10|5|1|2|6|4|1|2|2|6|5|0|2|2|0|3|1|0|0|4|0|0|8|0|0|0|0|0|6|0|2|0|0|3|0|0|0|0|4|0|0|0|0|0|0|0|0|0|0|0|0|0|0|0|0|0|0|0|0|0|1|0|0|0|0|0|2|0|0|0|0|0|0|0|0|0|1|0|0|0|0|0|0|0|1</HistCounts>
      </HistItem>
    </Histograms>
    <Metadata>
      <MDI key="BandName">nd</MDI>
      <MDI key="RepresentationType">ATHEMATIC</MDI>
      <MDI key="STATISTICS_COVARIANCES">0.003369192948716606</MDI>
      <MDI key="STATISTICS_EXCLUDEDVALUES"></MDI>
      <MDI key="STATISTICS_MAXIMUM">0.5407800078392</MDI>
      <MDI key="STATISTICS_MEAN">0.14215348487258</MDI>
      <MDI key="STATISTICS_MINIMUM">-0.10253320634365</MDI>
      <MDI key="STATISTICS_SKIPFACTORX">1</MDI>
      <MDI key="STATISTICS_SKIPFACTORY">1</MDI>
      <MDI key="STATISTICS_STDDEV">0.058044749536169</MDI>
    </Metadata>
  </PAMRasterBand>
</PAMDataset>
