<PAMDataset>
  <Metadata>
    <MDI key="DataType">Generic</MDI>
  </Metadata>
  <PAMRasterBand band="1">
    <Description>nd</Description>
    <Histograms>
      <HistItem>
        <HistMin>0.256060004234314</HistMin>
        <HistMax>0.8081921935081482</HistMax>
        <BucketCount>256</BucketCount>
        <IncludeOutOfRange>1</IncludeOutOfRange>
        <Approximate>0</Approximate>
        <HistCounts>1|0|2|1|3|0|0|0|0|5|0|0|1|10|0|2|1|0|1|2|2|3|0|3|5|7|1|5|6|2|2|8|3|4|1|5|9|18|5|7|7|3|7|2|11|8|14|16|17|6|11|5|10|5|5|14|12|29|16|17|12|25|33|10|23|4|31|22|31|32|66|24|37|40|46|34|31|48|60|58|29|35|25|47|31|54|50|34|49|33|65|57|30|51|59|24|60|78|78|62|70|61|57|50|76|70|71|79|70|63|81|77|60|84|62|83|98|70|86|50|78|80|109|113|99|96|104|89|109|50|103|92|93|97|102|78|83|104|182|76|92|86|90|121|95|89|62|97|96|97|96|152|95|97|93|116|96|103|80|134|138|144|103|99|134|95|116|121|101|113|68|88|124|110|93|111|102|89|74|102|107|115|134|71|60|79|85|73|97|83|86|106|85|56|69|58|58|44|75|67|66|60|65|56|81|43|62|55|59|51|69|30|31|32|31|16|36|20|41|22|34|20|16|12|30|16|20|17|11|3|15|2|11|0|2|4|4|4|0|12|4|4|0|2|4|3|7|0|0|0|0|0|0|0|0|8</HistCounts>
      </HistItem>
    </Histograms>
    <Metadata>
      <MDI key="BandName">nd</MDI>
      <MDI key="RepresentationType">ATHEMATIC</MDI>
      <MDI key="STATISTICS_COVARIANCES">0.008614928677140877</MDI>
      <MDI key="STATISTICS_EXCLUDEDVALUES"></MDI>
      <MDI key="STATISTICS_MAXIMUM">0.80819219350815</MDI>
      <MDI key="STATISTICS_MEAN">0.57031720797946</MDI>
      <MDI key="STATISTICS_MINIMUM">0.25606000423431</MDI>
      <MDI key="STATISTICS_SKIPFACTORX">1</MDI>
      <MDI key="STATISTICS_SKIPFACTORY">1</MDI>
      <MDI key="STATISTICS_STDDEV">0.092816640087545</MDI>
    </Metadata>
  </PAMRasterBand>
</PAMDataset>
