<PAMDataset>
  <Metadata>
    <MDI key="DataType">Generic</MDI>
  </Metadata>
  <PAMRasterBand band="1">
    <Description>nd</Description>
    <Histograms>
      <HistItem>
        <HistMin>-0.006018773652613163</HistMin>
        <HistMax>0.2074126899242401</HistMax>
        <BucketCount>256</BucketCount>
        <IncludeOutOfRange>1</IncludeOutOfRange>
        <Approximate>0</Approximate>
        <HistCounts>1|0|0|3|0|1|1|0|0|0|1|0|0|0|0|1|0|0|2|4|4|3|1|0|2|0|7|0|4|2|3|4|4|3|0|8|5|12|22|12|17|19|13|19|22|12|10|19|11|39|36|41|53|14|33|30|61|19|48|55|39|44|77|99|99|106|167|168|186|140|242|233|254|244|353|318|341|341|319|368|372|448|380|367|338|339|416|372|351|326|267|326|277|314|282|269|302|258|276|249|267|263|234|238|221|218|197|231|158|124|141|156|162|145|142|124|165|138|139|125|157|113|162|126|159|174|142|138|158|176|157|158|163|154|151|136|137|205|161|193|136|133|171|139|152|142|94|139|129|148|136|128|114|126|97|88|95|175|69|102|78|103|100|111|126|56|60|84|79|59|73|48|39|46|30|35|23|58|52|33|28|24|39|41|37|20|26|10|22|30|34|30|16|43|16|18|9|19|19|22|9|12|2|4|12|6|12|13|5|8|4|4|8|8|8|3|0|4|4|4|6|0|4|1|0|4|4|4|0|4|0|0|0|0|0|0|0|0|0|0|0|2|0|0|0|0|0|0|0|0|0|0|0|0|2|4</HistCounts>
      </HistItem>
    </Histograms>
    <Metadata>
      <MDI key="BandName">nd</MDI>
      <MDI key="RepresentationType">ATHEMATIC</MDI>
      <MDI key="STATISTICS_COVARIANCES">0.0008149703013081198</MDI>
      <MDI key="STATISTICS_EXCLUDEDVALUES"></MDI>
      <MDI key="STATISTICS_MAXIMUM">0.20741268992424</MDI>
      <MDI key="STATISTICS_MEAN">0.084496072728432</MDI>
      <MDI key="STATISTICS_MINIMUM">-0.0060187736526132</MDI>
      <MDI key="STATISTICS_SKIPFACTORX">1</MDI>
      <MDI key="STATISTICS_SKIPFACTORY">1</MDI>
      <MDI key="STATISTICS_STDDEV">0.0285476846926</MDI>
    </Metadata>
  </PAMRasterBand>
</PAMDataset>
