<?xml version="1.0" encoding="UTF-8"?>
<metadata xml:lang="en"><Esri><CreaDate>20240421</CreaDate><CreaTime>14561700</CreaTime><ArcGISFormat>1.0</ArcGISFormat><SyncOnce>TRUE</SyncOnce><DataProperties><lineage><Process ToolSource="c:\application\desktop10.8\ArcToolbox\Toolboxes\Conversion Tools.tbx\RasterToPolygon" Date="20240421" Time="145617">RasterToPolygon "C:\Application\Crop-Yield-Prediction\Data\Province LandCover (2000 - 2020)\Quang_Ninh\2013.tif" "C:\Application\Crop-Yield-Prediction\Data\Province LandCover Shape (2000 - 2020)\Quang_Ninh\2013.shp" NO_SIMPLIFY Value SINGLE_OUTER_PART #</Process><Process ToolSource="c:\application\desktop10.8\ArcToolbox\Toolboxes\Data Management Tools.tbx\AddField" Date="20240421" Time="152139">AddField "C:\Application\Crop-Yield-Prediction\Data\Province LandCover Shape (2000 - 2020)\Quang_Ninh\2013.shp" area DOUBLE # # # # NULLABLE NON_REQUIRED #</Process></lineage></DataProperties></Esri></metadata>
