<PAMDataset>
  <Metadata>
    <MDI key="DataType">Generic</MDI>
  </Metadata>
  <PAMRasterBand band="1">
    <Description>nd</Description>
    <Histograms>
      <HistItem>
        <HistMin>0.1841032952070236</HistMin>
        <HistMax>0.8794331550598145</HistMax>
        <BucketCount>256</BucketCount>
        <IncludeOutOfRange>1</IncludeOutOfRange>
        <Approximate>0</Approximate>
        <HistCounts>1|0|0|0|0|0|0|0|0|0|0|0|0|0|0|0|0|0|0|0|0|0|1|3|0|0|0|1|0|0|0|0|0|0|2|2|0|0|0|0|0|0|0|0|0|0|0|0|1|5|0|0|0|0|0|1|4|0|2|0|0|0|2|2|1|0|0|4|1|0|1|3|0|1|0|4|0|4|0|1|0|0|0|1|2|0|4|2|1|0|4|2|7|2|2|5|3|0|0|2|5|1|2|4|5|12|8|11|11|4|3|8|19|4|4|8|4|0|9|8|12|10|7|8|4|13|6|27|6|5|12|13|10|11|12|12|16|7|14|16|23|26|25|16|14|35|27|17|23|13|29|32|20|24|32|29|36|32|36|65|37|22|40|50|69|51|55|55|41|55|56|74|72|68|67|60|67|46|71|64|87|68|83|100|79|76|95|111|106|95|117|135|134|161|135|109|129|85|172|112|98|125|159|131|180|173|149|132|150|144|223|216|199|177|174|167|188|260|162|170|211|159|202|219|219|202|163|234|220|159|125|159|161|145|174|77|114|111|62|46|48|42|38|24|18|28|13|14|10|2|4|4|0|0|0|4</HistCounts>
      </HistItem>
    </Histograms>
    <Metadata>
      <MDI key="BandName">nd</MDI>
      <MDI key="RepresentationType">ATHEMATIC</MDI>
      <MDI key="STATISTICS_COVARIANCES">0.006483388278788299</MDI>
      <MDI key="STATISTICS_EXCLUDEDVALUES"></MDI>
      <MDI key="STATISTICS_MAXIMUM">0.87943315505981</MDI>
      <MDI key="STATISTICS_MEAN">0.73436947942624</MDI>
      <MDI key="STATISTICS_MINIMUM">0.18410329520702</MDI>
      <MDI key="STATISTICS_SKIPFACTORX">1</MDI>
      <MDI key="STATISTICS_SKIPFACTORY">1</MDI>
      <MDI key="STATISTICS_STDDEV">0.080519490055441</MDI>
    </Metadata>
  </PAMRasterBand>
</PAMDataset>
