<PAMDataset>
  <Metadata>
    <MDI key="DataType">Generic</MDI>
  </Metadata>
  <PAMRasterBand band="1">
    <Description>nd</Description>
    <Histograms>
      <HistItem>
        <HistMin>-0.4079408049583435</HistMin>
        <HistMax>0.8376277089118958</HistMax>
        <BucketCount>256</BucketCount>
        <IncludeOutOfRange>1</IncludeOutOfRange>
        <Approximate>0</Approximate>
        <HistCounts>1|0|0|0|0|0|0|0|0|0|0|0|0|2|0|0|0|0|0|0|0|0|0|0|0|0|0|0|0|0|0|0|0|0|0|0|0|0|0|0|0|0|0|0|0|0|0|0|0|0|0|0|0|0|0|0|0|0|0|0|0|0|0|0|0|0|0|0|0|0|0|0|0|0|0|0|0|0|0|0|4|1|0|4|4|4|0|0|0|0|5|0|4|3|0|0|2|3|2|7|0|5|5|2|4|6|8|6|14|11|6|2|13|19|0|7|22|12|8|5|16|8|19|14|11|4|21|3|20|13|13|19|19|31|29|17|8|26|10|14|18|22|16|14|5|11|10|17|35|21|49|13|43|40|28|10|19|38|11|13|24|30|28|42|21|35|56|41|46|49|43|55|59|76|59|54|54|52|77|68|65|98|80|115|103|67|91|90|76|120|113|147|104|124|137|173|171|218|167|196|204|273|229|253|253|230|354|336|266|295|405|505|357|479|453|491|494|558|537|557|569|563|692|620|584|527|655|591|549|430|452|473|297|251|173|106|89|87|46|25|50|10|10|10|14|20|14|8|8|10|12|4|4|0|0|4</HistCounts>
      </HistItem>
    </Histograms>
    <Metadata>
      <MDI key="BandName">nd</MDI>
      <MDI key="RepresentationType">ATHEMATIC</MDI>
      <MDI key="STATISTICS_COVARIANCES">0.01318246743968975</MDI>
      <MDI key="STATISTICS_EXCLUDEDVALUES"></MDI>
      <MDI key="STATISTICS_MAXIMUM">0.8376277089119</MDI>
      <MDI key="STATISTICS_MEAN">0.61703623778382</MDI>
      <MDI key="STATISTICS_MINIMUM">-0.40794080495834</MDI>
      <MDI key="STATISTICS_SKIPFACTORX">1</MDI>
      <MDI key="STATISTICS_SKIPFACTORY">1</MDI>
      <MDI key="STATISTICS_STDDEV">0.11481492690278</MDI>
    </Metadata>
  </PAMRasterBand>
</PAMDataset>
